cityscapesscripts/VERSION
cityscapesscripts/__init__.py
cityscapesscripts/annotation/__init__.py
cityscapesscripts/annotation/cityscapesLabelTool.py
cityscapesscripts/annotation/icons/back.png
cityscapesscripts/annotation/icons/checked6.png
cityscapesscripts/annotation/icons/checked6_red.png
cityscapesscripts/annotation/icons/clearpolygon.png
cityscapesscripts/annotation/icons/deleteobject.png
cityscapesscripts/annotation/icons/exit.png
cityscapesscripts/annotation/icons/filepath.png
cityscapesscripts/annotation/icons/help19.png
cityscapesscripts/annotation/icons/highlight.png
cityscapesscripts/annotation/icons/layerdown.png
cityscapesscripts/annotation/icons/layerup.png
cityscapesscripts/annotation/icons/minus.png
cityscapesscripts/annotation/icons/modify.png
cityscapesscripts/annotation/icons/newobject.png
cityscapesscripts/annotation/icons/next.png
cityscapesscripts/annotation/icons/open.png
cityscapesscripts/annotation/icons/play.png
cityscapesscripts/annotation/icons/plus.png
cityscapesscripts/annotation/icons/save.png
cityscapesscripts/annotation/icons/screenshot.png
cityscapesscripts/annotation/icons/screenshotToggle.png
cityscapesscripts/annotation/icons/shuffle.png
cityscapesscripts/annotation/icons/undo.png
cityscapesscripts/annotation/icons/zoom.png
cityscapesscripts/download/__init__.py
cityscapesscripts/download/downloader.py
cityscapesscripts/evaluation/__init__.py
cityscapesscripts/evaluation/evalInstanceLevelSemanticLabeling.py
cityscapesscripts/evaluation/evalObjectDetection3d.py
cityscapesscripts/evaluation/evalPanopticSemanticLabeling.py
cityscapesscripts/evaluation/evalPixelLevelSemanticLabeling.py
cityscapesscripts/evaluation/instance.py
cityscapesscripts/evaluation/instances2dict.py
cityscapesscripts/evaluation/objectDetectionHelpers.py
cityscapesscripts/evaluation/plot3dResults.py
cityscapesscripts/helpers/__init__.py
cityscapesscripts/helpers/annotation.py
cityscapesscripts/helpers/box3dImageTransform.py
cityscapesScripts-2.2.4.dist-info/LICENSE
cityscapesScripts-2.2.4.dist-info/METADATA
cityscapesScripts-2.2.4.dist-info/WHEEL
cityscapesScripts-2.2.4.dist-info/entry_points.txt
cityscapesScripts-2.2.4.dist-info/top_level.txt
cityscapesScripts-2.2.4.dist-info/RECORD
