Metadata-Version: 2.1
Name: cityscapesScripts
Version: 2.2.4
Summary: Scripts for the Cityscapes Dataset
Home-page: https://github.com/mcordts/cityscapesScripts
Author: Marius Cordts
Author-email: mail@cityscapes-dataset.net
License: https://github.com/mcordts/cityscapesScripts/blob/master/LICENSE
License-File: LICENSE
Requires-Dist: numpy
Requires-Dist: matplotlib
Requires-Dist: pillow
Requires-Dist: appdirs
Requires-Dist: pyquaternion
Requires-Dist: coloredlogs
Requires-Dist: tqdm
Requires-Dist: typing
Requires-Dist: requests
Provides-Extra: gui
Requires-Dist: PyQt5 ; extra == 'gui'
